typer_cloup_cli/__init__.py
typer_cloup_cli/__main__.py
typer_cloup_cli/main.py
typer_cloup_cli-0.4.0.dist-info/METADATA
typer_cloup_cli-0.4.0.dist-info/entry_points.txt
typer_cloup_cli-0.4.0.dist-info/WHEEL
typer_cloup_cli-0.4.0.dist-info/LICENSE
typer_cloup_cli-0.4.0.dist-info/RECORD
