Metadata-Version: 2.1
Name: typer-cloup-cli
Version: 0.4.0
Summary: Run Typer scripts with completion, without having to create a package, using Typer CLI.
Home-page: https://github.com/alexreg/typer-cloup-cli
License: MIT
Keywords: cli,click,cloup,shell,terminal,typer
Author: Sebastián Ramírez
Author-email: tiangolo@gmail.com
Maintainer: Alexander Regueiro
Maintainer-email: alex@noldorin.com
Requires-Python: >=3.7,<4.0
Classifier: Development Status :: 4 - Beta
Classifier: Environment :: Console
Classifier: Intended Audience :: Developers
Classifier: Intended Audience :: Education
Classifier: Intended Audience :: End Users/Desktop
Classifier: Intended Audience :: Information Technology
Classifier: Intended Audience :: System Administrators
Classifier: License :: OSI Approved :: MIT License
Classifier: Operating System :: OS Independent
Classifier: Programming Language :: Python
Classifier: Programming Language :: Python :: 3
Classifier: Programming Language :: Python :: 3.7
Classifier: Programming Language :: Python :: 3.8
Classifier: Programming Language :: Python :: 3.9
Classifier: Programming Language :: Python :: 3.10
Classifier: Programming Language :: Python :: 3.11
Classifier: Programming Language :: Python :: 3
Classifier: Programming Language :: Python :: 3 :: Only
Classifier: Programming Language :: Python :: 3.10
Classifier: Programming Language :: Python :: 3.7
Classifier: Programming Language :: Python :: 3.8
Classifier: Programming Language :: Python :: 3.9
Classifier: Topic :: Software Development
Classifier: Topic :: Software Development :: Libraries
Classifier: Topic :: Software Development :: Libraries :: Application Frameworks
Classifier: Topic :: Software Development :: Libraries :: Python Modules
Classifier: Topic :: Terminals
Classifier: Topic :: Utilities
Classifier: Typing :: Typed
Requires-Dist: colorama (>=0.4.4,<0.5.0)
Requires-Dist: docstring_parser (>=0.15,<0.16)
Requires-Dist: shellingham (>=1.4.0,<2.0.0)
Requires-Dist: typer-cloup (>=0.11.0,<0.12.0)
Project-URL: Documentation, https://typer-cloup.netlify.app/typer-cli/
Project-URL: Repository, https://github.com/alexreg/typer-cloup-cli
